{
    "room_config": {
        "min_player": 1,
        "max_player": 50,
        "default_num_player": 1,
        "default_map": 0,
        "default_tank": "tank1",
        "max_item_on_map" : 10,
        "max_jet_plane_on_map": 3
    },
    "tanks": [
        {
            "type": "tank0",
            "hp": 1000,
            "width": 120,
            "height": 70,
            "min_speed": 100,
            "max_speed": 600,
            "bullet_rate": 400,
            "bullet_type": "bullet0",
            "rotation_speed": 6,
            "cannon_length": 80,
            "max_bullets": 10,
            "time_reload_bullet":2000
        },
        {
            "type": "tank1",
            "hp": 1500,
            "width": 130,
            "height": 94,
            "min_speed": 100,
            "max_speed": 450,
            "bullet_rate": 600,
            "bullet_type": "bullet0",
            "rotation_speed": 6,
            "cannon_length": 90,
            "max_bullets": 11,
            "time_reload_bullet":2000
        },
        {
            "type": "tank2",
            "hp": 1200,
            "width": 125,
            "height": 76,
            "min_speed": 100,
            "max_speed": 510,
            "bullet_rate": 500,
            "bullet_type": "bullet0",
            "rotation_speed": 6,
            "cannon_length": 90,
            "max_bullets": 12,
            "time_reload_bullet":2000
        }
    ],
    "bullets": [
        {
            "type": "bullet0",
            "speed": 1600,
            "damage": 100,
            "geometry": "circle",
            "radius": 10
        }
    ],
    "jet_plane": {
        "speed": 500
    },
    "items": {
        "radius": 40,
        "time_alive": 9000,
        "time_to_appear": 2000
    },
    "effects": [
        {
            "type": 0,
            "name": "heal",
            "duration": 5000,
            "healRate": 100
        },
        {
            "type": 1,
            "name": "shield",
            "duration": 5000,
            "radius": 150
        }
    ]
}